galileo/README_API_CLIENT.md
galileo/__future__/__init__.py
galileo/__future__/configuration.py
galileo/__future__/dataset.py
galileo/__future__/experiment.py
galileo/__future__/integration.py
galileo/__future__/log_stream.py
galileo/__future__/metric.py
galileo/__future__/model.py
galileo/__future__/project.py
galileo/__future__/prompt.py
galileo/__future__/provider.py
galileo/__future__/shared/__init__.py
galileo/__future__/shared/base.py
galileo/__future__/shared/column.py
galileo/__future__/shared/exceptions.py
galileo/__future__/shared/experiment_result.py
galileo/__future__/shared/filter.py
galileo/__future__/shared/query_result.py
galileo/__future__/shared/sort.py
galileo/__future__/shared/utils.py
galileo/__future__/types.py
galileo/__init__.py
galileo/config.py
galileo/constants/__init__.py
galileo/constants/protect.py
galileo/constants/routes.py
galileo/constants/tracing.py
galileo/datasets.py
galileo/decorator.py
galileo/exceptions.py
galileo/experiment_tags.py
galileo/experiments.py
galileo/export.py
galileo/handlers/base_async_handler.py
galileo/handlers/base_handler.py
galileo/handlers/crewai/__init__.py
galileo/handlers/crewai/handler.py
galileo/handlers/langchain/__init__.py
galileo/handlers/langchain/async_handler.py
galileo/handlers/langchain/handler.py
galileo/handlers/langchain/tool.py
galileo/handlers/langchain/utils.py
galileo/handlers/openai_agents/__init__.py
galileo/handlers/openai_agents/handler.py
galileo/job_progress.py
galileo/jobs.py
galileo/log_streams.py
galileo/logger/__init__.py
galileo/logger/logger.py
galileo/logger/task_handler.py
galileo/logger/utils.py
galileo/metrics.py
galileo/middleware/__init__.py
galileo/middleware/tracing.py
galileo/openai.py
galileo/otel.py
galileo/projects.py
galileo/prompts.py
galileo/protect.py
galileo/resources/__init__.py
galileo/resources/api/__init__.py
galileo/resources/api/auth/__init__.py
galileo/resources/api/auth/login_api_key_login_api_key_post.py
galileo-1.39.0.dist-info/LICENSE
galileo-1.39.0.dist-info/METADATA
galileo-1.39.0.dist-info/WHEEL
galileo-1.39.0.dist-info/RECORD
