Metadata-Version: 2.3
Name: galileo
Version: 1.39.0
Summary: Client library for the Galileo platform.
License: Apache-2.0
Author: Galileo Technologies Inc.
Author-email: team@galileo.ai
Requires-Python: >=3.9,<3.14
Classifier: License :: OSI Approved :: Apache Software License
Classifier: Programming Language :: Python :: 3
Classifier: Programming Language :: Python :: 3.9
Classifier: Programming Language :: Python :: 3.10
Classifier: Programming Language :: Python :: 3.11
Classifier: Programming Language :: Python :: 3.12
Classifier: Programming Language :: Python :: 3.13
Provides-Extra: all
Provides-Extra: crewai
Provides-Extra: langchain
Provides-Extra: middleware
Provides-Extra: openai
Provides-Extra: otel
Requires-Dist: attrs (>=22.2.0)
Requires-Dist: backoff (>=2.2.1,<3.0.0)
Requires-Dist: crewai (>=0.152.0,<=0.201.1) ; extra == "all"
Requires-Dist: crewai (>=0.152.0,<=0.201.1) ; extra == "crewai"
Requires-Dist: galileo-core (>=3.75.0,<4.0.0)
Requires-Dist: langchain-core ; extra == "all"
Requires-Dist: langchain-core ; extra == "langchain"
Requires-Dist: openai ; extra == "all"
Requires-Dist: openai ; extra == "openai"
Requires-Dist: openai-agents ; extra == "all"
Requires-Dist: openai-agents ; extra == "openai"
Requires-Dist: opentelemetry-api (>=1.38.0,<2.0.0) ; extra == "all"
Requires-Dist: opentelemetry-api (>=1.38.0,<2.0.0) ; extra == "otel"
Requires-Dist: opentelemetry-exporter-otlp (>=1.38.0,<2.0.0) ; extra == "all"
Requires-Dist: opentelemetry-exporter-otlp (>=1.38.0,<2.0.0) ; extra == "otel"
Requires-Dist: opentelemetry-sdk (>=1.38.0,<2.0.0) ; extra == "all"
Requires-Dist: opentelemetry-sdk (>=1.38.0,<2.0.0) ; extra == "otel"
Requires-Dist: packaging (>=24.2,<25.0) ; extra == "all"
Requires-Dist: packaging (>=24.2,<25.0) ; extra == "openai"
Requires-Dist: pydantic (>=2.11.7,<3.0.0)
Requires-Dist: pyjwt (>=2.8.0,<3.0.0)
Requires-Dist: python-dateutil (>=2.8.0,<3.0.0)
Requires-Dist: starlette ; extra == "all"
Requires-Dist: starlette ; extra == "middleware"
Requires-Dist: wrapt (>=1.14,<2.0)
Project-URL: Repository, https://github.com/rungalileo/galileo-python
